{
  "id": "custom-footer-7",
  "name": "Footer 7",
  "description": "Section: Footer 7",
  "tags": [
    "footer"
  ],
  "type": "custom",
  "liquid_code": "{%- liquid \n  assign padding_horizontal = section.settings.padding_horizontal\n  assign padding_horizontal_mobile = section.settings.padding_horizontal_mobile\n  assign padding_top = section.settings.padding_top\n  assign padding_bottom = section.settings.padding_bottom\n  assign border_color = section.settings.border_color\n  assign border_thickness = section.settings.border_thickness\n  assign margin_top = section.settings.margin_top\n  assign margin_bottom = section.settings.margin_bottom\n  assign margin_horizontal_mobile = section.settings.margin_horizontal_mobile\n  assign margin_horizontal = section.settings.margin_horizontal\n  assign background_color = section.settings.background_color\n  assign background_gradient = section.settings.background_gradient\n  assign full_width = section.settings.full_width\n  assign content_width = section.settings.content_width\n  assign lazy = section.settings.lazy\n  assign section_radius = section.settings.section_radius\n\n  assign block_padding_vertical = section.settings.block_padding_vertical\n  assign block_padding_vertical_mobile = section.settings.block_padding_vertical_mobile\n  assign block_padding_horizontal = section.settings.block_padding_horizontal\n  assign block_padding_horizontal_mobile = section.settings.block_padding_horizontal_mobile\n  assign block_border_thickness = section.settings.block_border_thickness\n  assign block_border_color = section.settings.block_border_color\n\n  assign text = section.settings.text\n  assign text_size = section.settings.text_size\n  assign text_size_mobile = section.settings.text_size_mobile\n  assign text_color = section.settings.text_color\n  assign text_custom = section.settings.text_custom\n  assign text_font = section.settings.text_font\n  assign text_height = section.settings.text_height\n  assign text_align = section.settings.text_align\n  assign text_align_mobile = section.settings.text_align_mobile\n\n  assign use_newsletter = section.settings.use_newsletter\n  assign newsletter_gap = section.settings.newsletter_gap\n  assign newsletter_gap_mobile = section.settings.newsletter_gap_mobile\n  assign newsletter_mt = section.settings.newsletter_mt\n  assign newsletter_mt_mobile = section.settings.newsletter_mt_mobile\n  assign newsletter_radius = section.settings.newsletter_radius\n  assign newsletter_border_thickness = section.settings.newsletter_border_thickness\n  assign newsletter_border_color = section.settings.newsletter_border_color\n  assign use_redirect = section.settings.use_redirect\n  assign redirect_url = section.settings.redirect_url\n\n  assign input_size = section.settings.input_size\n  assign input_size_mobile = section.settings.input_size_mobile\n  assign input_color = section.settings.input_color\n  assign input_custom = section.settings.input_custom\n  assign input_font = section.settings.input_font\n  assign input_height = section.settings.input_height\n  assign input_padding_vertical = section.settings.input_padding_vertical\n  assign input_padding_vertical_mobile = section.settings.input_padding_vertical_mobile\n  assign input_padding_horizontal = section.settings.input_padding_horizontal\n  assign input_padding_horizontal_mobile = section.settings.input_padding_horizontal_mobile\n  assign input_radius = section.settings.input_radius\n  assign input_border_thickness = section.settings.input_border_thickness\n  assign input_border_color = section.settings.input_border_color\n  assign input_placeholder_color = section.settings.input_placeholder_color\n  assign input_bg_color = section.settings.input_bg_color\n\n  assign thanks_text = section.settings.thanks_text\n  assign thanks_text_size = section.settings.thanks_text_size\n  assign thanks_text_size_mobile = section.settings.thanks_text_size_mobile\n  assign thanks_text_color = section.settings.thanks_text_color\n  assign thanks_text_custom = section.settings.thanks_text_custom\n  assign thanks_text_font = section.settings.thanks_text_font\n  assign thanks_text_height = section.settings.thanks_text_height\n  assign thanks_text_mt = section.settings.thanks_text_mt\n  assign thanks_text_mt_mobile = section.settings.thanks_text_mt_mobile\n\n  assign input_placeholder = section.settings.input_placeholder\n\n  assign submit = section.settings.submit\n  assign submit_size = section.settings.submit_size\n  assign submit_size_mobile = section.settings.submit_size_mobile\n  assign submit_color = section.settings.submit_color\n  assign submit_hover_color = section.settings.submit_hover_color\n  assign submit_custom = section.settings.submit_custom\n  assign submit_font = section.settings.submit_font\n  assign submit_height = section.settings.submit_height\n  assign submit_padding_vertical = section.settings.submit_padding_vertical\n  assign submit_padding_vertical_mobile = section.settings.submit_padding_vertical_mobile\n  assign submit_padding_horizontal = section.settings.submit_padding_horizontal\n  assign submit_padding_horizontal_mobile = section.settings.submit_padding_horizontal_mobile\n  assign submit_radius = section.settings.submit_radius\n  assign submit_border_thickness = section.settings.submit_border_thickness\n  assign submit_border_color = section.settings.submit_border_color\n  assign submit_border_hover_color = section.settings.submit_border_hover_color\n  assign submit_bg_color = section.settings.submit_bg_color\n  assign submit_bg_hover_color = section.settings.submit_bg_hover_color\n\n  assign privacy_text = section.settings.privacy_text\n  assign privacy_text_size = section.settings.privacy_text_size\n  assign privacy_text_size_mobile = section.settings.privacy_text_size_mobile\n  assign privacy_text_color = section.settings.privacy_text_color\n  assign privacy_text_custom = section.settings.privacy_text_custom\n  assign privacy_text_font = section.settings.privacy_text_font\n  assign privacy_text_height = section.settings.privacy_text_height\n  assign privacy_text_align = section.settings.privacy_text_align\n  assign privacy_text_align_mobile = section.settings.privacy_text_align_mobile\n  assign privacy_text_mt = section.settings.privacy_text_mt\n  assign privacy_text_mt_mobile = section.settings.privacy_text_mt_mobile\n\n  assign column_heading_size = section.settings.column_heading_size\n  assign column_heading_size_mobile = section.settings.column_heading_size_mobile\n  assign column_heading_color = section.settings.column_heading_color\n  assign column_heading_custom = section.settings.column_heading_custom\n  assign column_heading_font = section.settings.column_heading_font\n  assign column_heading_height = section.settings.column_heading_height\n\n  assign list_gap_mobile = section.settings.list_gap_mobile\n  assign list_gap = section.settings.list_gap\n  assign list_mt = section.settings.list_mt\n  assign list_mt_mobile = section.settings.list_mt_mobile\n\n  assign link_size = section.settings.link_size\n  assign link_size_mobile = section.settings.link_size_mobile\n  assign link_color = section.settings.link_color\n  assign link_hover_color = section.settings.link_hover_color\n  assign link_custom = section.settings.link_custom\n  assign link_font = section.settings.link_font\n  assign link_height = section.settings.link_height\n\n  assign column_text_size = section.settings.column_text_size\n  assign column_text_size_mobile = section.settings.column_text_size_mobile\n  assign column_text_color = section.settings.column_text_color\n  assign column_text_custom = section.settings.column_text_custom\n  assign column_text_font = section.settings.column_text_font\n  assign column_text_height = section.settings.column_text_height\n  assign column_text_mt = section.settings.column_text_mt\n  assign column_text_mt_mobile = section.settings.column_text_mt_mobile\n  \n-%}\n\n{%- style -%}\n\n  {{  text_font | font_face: font_display: 'swap' }}\n  {{  input_font | font_face: font_display: 'swap' }}\n  {{  submit_font | font_face: font_display: 'swap' }}\n  {{  privacy_text_font | font_face: font_display: 'swap' }}\n  {{  column_heading_font | font_face: font_display: 'swap' }}\n  {{  link_font | font_face: font_display: 'swap' }}\n  {{  column_text_font | font_face: font_display: 'swap' }}\n  {{  thanks_text_font | font_face: font_display: 'swap' }}      \n  \n  .section-{{ section.id }} {\n    border-top: solid {{ border_color }} {{ border_thickness }}px;\n    border-bottom: solid {{ border_color }} {{ border_thickness }}px;\n    margin-top: {{ margin_top | times: 0.75 | round: 0 }}px;\n    margin-bottom: {{ margin_bottom | times: 0.75 | round: 0 }}px;\n    margin-left: {{ margin_horizontal_mobile }}rem;\n    margin-right: {{ margin_horizontal_mobile }}rem;\n    border-radius: {{ section_radius | times: 0.6 | round: 0 }}px;\n    overflow: hidden;\n  }\n  \n  .section-{{ section.id }}-settings {\n    margin: 0 auto;\n    padding-top: {{ padding_top | times: 0.75 | round: 0 }}px;\n    padding-bottom: {{ padding_bottom | times: 0.75 | round: 0 }}px;\n    padding-left: {{ padding_horizontal_mobile }}rem;\n    padding-right: {{ padding_horizontal_mobile }}rem;\n  }\n\n  .footer-body-{{ section.id }} {\n    display: grid;\n    grid-template-columns: 1fr;\n  }\n\n  .footer-left-{{ section.id }},\n  .footer-right-{{ section.id }} {\n    padding: {{ block_padding_vertical_mobile }}px {{ block_padding_horizontal_mobile }}px;\n  }\n\n  .footer-right-{{ section.id }} {\n    display: flex;\n    align-items: stretch;\n    gap: 20px;\n    flex-wrap: wrap;\n    border-top: {{ block_border_thickness }}px solid {{ block_border_color }};\n  }\n\n  .footer-column-{{ section.id }} {\n    flex: 1 0;\n  }\n\n  .footer-text-column-{{ section.id }} {\n    flex: 1 0 100%;\n  }\n\n  .footer-text-{{ section.id }} {\n    text-align: {{ text_align_mobile }};\n  }\n\n  .footer-text-{{ section.id }} * {\n    margin: 0;\n    font-size: {{ text_size_mobile }}px;\n    color: {{ text_color }};\n    line-height: {{ text_height }}%;\n    text-transform: unset;\n  }\n\n  .footer-newsletter-row-{{ section.id }} {\n    position: relative;\n    display: flex;\n    align-items: stretch;\n    gap: {{ newsletter_gap_mobile }}px;\n    border-radius: {{ newsletter_radius }}px;\n    overflow: hidden;\n    margin-top: {{ newsletter_mt_mobile }}px;\n  }\n\n  .footer-newsletter-input-{{ section.id }} {\n    width: 100%;\n    margin: 0;\n    box-shadow: none;\n    border: 0px;\n    padding: {{ input_padding_vertical_mobile }}px {{ input_padding_horizontal_mobile }}px;\n    font-size: {{ input_size_mobile }}px;\n    color: {{ input_color }};\n    line-height: {{ input_height }}%;\n    text-transform: unset;\n    border-radius: {{ input_radius }}px;\n    border: {{ input_border_thickness }}px solid {{ input_border_color }};\n    background-color: transparent;\n    background-color: {{ input_bg_color }};\n  }\n\n  .footer-newsletter-input-{{ section.id }}:focus,\n  .footer-newsletter-input-{{ section.id }}:focus-visible {\n    outline: none;\n    box-shadow: none;\n  }\n\n  .footer-newsletter-input-{{ section.id }}::placeholder {\n    color: {{ input_placeholder_color }};\n  }\n\n  .footer-newsletter-submit-{{ section.id }} {\n    margin-top: 0px;\n    width: 100%;\n    max-width: fit-content;\n    display: flex;\n    align-items: center;\n    justify-content: center;\n    font-size: {{ submit_size_mobile }}px;\n    color: {{ submit_color }};\n    line-height: {{ submit_height }}%;\n    text-align: center;\n    text-transform: unset;\n    text-decoration: none;\n    padding: {{ submit_padding_vertical_mobile }}px {{ submit_padding_horizontal_mobile }}px;\n    border-radius: {{ submit_radius }}px;\n    border: 0px;\n    border: {{ submit_border_thickness }}px solid {{ submit_border_color }};\n    background-color: transparent;\n    background-color: {{ submit_bg_color }};\n    transition: all 0.25s ease 0s;\n    box-shadow: none;\n    cursor: pointer;\n    position: relative;\n  }\n\n  .footer-newsletter-submit-{{ section.id }}:hover {\n    color: {{ submit_hover_color }};\n    border: {{ submit_border_thickness }}px solid {{ submit_border_hover_color }};\n    background-color: {{ submit_bg_hover_color }};\n    transition: all 0.25s ease 0s;\n  }\n\n  .footer-newsletter-submit-{{ section.id }}::before {\n    content: '';\n    position: absolute;\n    left: -{{ newsletter_border_thickness }}px;\n    top: 0;\n    display: block;\n    width: {{ newsletter_border_thickness }}px;\n    height: 100%;\n    background-color: {{ newsletter_border_color }};\n  }\n\n .footer-newsletter-thanks-text-{{ section.id }} {\n    display: none;\n    margin: 0px;\n    margin-top: {{ thanks_text_mt_mobile }}px;\n    font-size: {{ thanks_text_size_mobile }}px;\n    color: {{ thanks_text_color }};\n    line-height: {{ thanks_text_height }}%;\n    text-transform: unset;\n }\n\n .footer-newsletter-thanks-text-{{ section.id }}.active {\n   display: block;\n }\n\n\n  .footer-privacy-text-{{ section.id }} {\n    margin-top: {{ privacy_text_mt_mobile }}px;\n    text-align: {{ privacy_text_align_mobile }};\n  }\n\n  .footer-privacy-text-{{ section.id }} * {\n    margin: 0;\n    font-size: {{ privacy_text_size_mobile }}px;\n    color: {{ privacy_text_color }};\n    line-height: {{ privacy_text_height }}%;\n    text-transform: unset;\n  }\n\n  .footer-column-heading-{{ section.id }} {\n    margin: 0;\n    font-size: {{ column_heading_size_mobile }}px;\n    color: {{ column_heading_color }};\n    line-height: {{ column_heading_height }}%;\n    text-transform: unset;\n    text-decoration: none;\n    font-weight: 700;\n  }\n\n  .footer-menu-list-{{ section.id }},\n  .footer-social-list-{{ section.id }} {\n    padding: 0px;\n    margin: 0px;\n    display: flex;\n    flex-direction: column;\n    gap: {{ list_gap_mobile }}px;\n    margin-top: {{ list_mt_mobile }}px;\n    list-style: none;\n  }\n\n  .footer-menu-item-{{ section.id }},\n  .footer-social-item-{{ section.id }} {\n    line-height: 100%;\n  }\n\n  .footer-menu-link-{{ section.id }},\n  .footer-social-link-{{ section.id }} {\n    margin: 0;\n    font-size: {{ link_size_mobile }}px;\n    color: {{ link_color }};\n    line-height: {{ link_height }}%;\n    text-transform: unset;\n    text-decoration: none;\n  }\n\n  .footer-social-link-{{ section.id }} {\n    display: flex;\n    align-items: center;\n    gap: 8px;\n  }\n\n  .footer-social-link-{{ section.id }} svg {\n    display: block;\n    width: 20px;\n    height: 20px;\n  }\n\n  .footer-social-link-{{ section.id }} svg path {\n    fill: {{ link_color }};\n    transition: all 0.25s ease 0s;\n  }\n\n  .footer-column-text-{{ section.id }} {\n    margin-top: {{ column_text_mt_mobile }}px;\n  }\n\n  .footer-column-text-{{ section.id }} * {\n    margin: 0;\n    font-size: {{ column_text_size_mobile }}px;\n    color: {{ column_text_color }};\n    line-height: {{ column_text_height }}%;\n    text-transform: unset;\n    text-decoration: none;\n  }\n\n  .footer-column-text-{{ section.id }} *:not(:first-child) {\n    margin-top: 10px;\n  }\n  \n  @media(min-width: 1024px) {\n\n    .section-{{ section.id }} {\n      margin-top: {{ margin_top }}px;\n      margin-bottom: {{ margin_bottom }}px;\n      margin-left: {{ margin_horizontal }}rem;\n      margin-right: {{ margin_horizontal }}rem;\n      border-radius: {{ section_radius }}px;\n    }\n    \n    .section-{{ section.id }}-settings {\n      padding: 0 5rem;\n      padding-top: {{ padding_top }}px;\n      padding-bottom: {{ padding_bottom }}px;\n      padding-left: {{ padding_horizontal }}rem;\n      padding-right: {{ padding_horizontal }}rem;\n    }\n\n    .footer-body-{{ section.id }} {\n      grid-template-columns: 40% 60%;\n    }\n\n    .footer-left-{{ section.id }},\n    .footer-right-{{ section.id }}{\n      padding: {{ block_padding_vertical }}px {{ block_padding_horizontal }}px;\n    }\n\n    .footer-right-{{ section.id }} {\n      border-top: 0px;\n      border-left: {{ block_border_thickness }}px solid {{ block_border_color }};\n    }\n\n    .footer-text-column-{{ section.id }} {\n      flex: 1 0 15%;\n    }\n\n    .footer-text-{{ section.id }} {\n      text-align: {{ text_align }};\n    }\n  \n    .footer-text-{{ section.id }} * {\n      font-size: {{ text_size }}px;\n    }\n\n    .footer-newsletter-row-{{ section.id }} {\n      margin-top: {{ newsletter_mt }}px;\n      gap: {{ newsletter_gap }}px;\n    }\n\n    .footer-newsletter-input-{{ section.id }} {\n      padding: {{ input_padding_vertical }}px {{ input_padding_horizontal }}px;\n      font-size: {{ input_size }}px;\n    }\n\n    .footer-newsletter-submit-{{ section.id }} {\n      padding: {{ submit_padding_vertical }}px {{ submit_padding_horizontal }}px;\n      font-size: {{ submit_size }}px;\n    }\n\n     .footer-newsletter-thanks-text-{{ section.id }} {\n     margin-top: {{ thanks_text_mt }}px;\n     font-size: {{ thanks_text_size }}px;\n   }\n\n    .footer-privacy-text-{{ section.id }} {\n      margin-top: {{ privacy_text_mt }}px;\n      text-align: {{ privacy_text_align }};\n    }\n  \n    .footer-privacy-text-{{ section.id }} * {\n      font-size: {{ privacy_text_size }}px;\n    }\n\n    .footer-column-heading-{{ section.id }} {\n      font-size: {{ column_heading_size }}px;\n    }\n\n    .footer-menu-list-{{ section.id }},\n    .footer-social-list-{{ section.id }}{\n      gap: {{ list_gap }}px;\n      margin-top: {{ list_mt }}px;\n    }\n\n    .footer-menu-link-{{ section.id }},\n    .footer-social-link-{{ section.id }} {\n      font-size: {{ link_size }}px;\n      transition: all 0.25s ease 0s;\n    }\n\n    .footer-menu-link-{{ section.id }}:hover,\n    .footer-social-link-{{ section.id }}:hover {\n      transition: all 0.25s ease 0s;\n      color: {{ link_hover_color }};\n    }\n\n    .footer-social-link-{{ section.id }}:hover svg path {\n       fill: {{ link_hover_color }};\n       transition: all 0.25s ease 0s;\n    }\n\n    .footer-column-text-{{ section.id }} {\n      margin-top: {{ column_text_mt }}px;\n    }\n  \n    .footer-column-text-{{ section.id }} * {\n      font-size: {{ column_text_size }}px;\n    }\n  }\n  \n{%- endstyle -%}\n\n{% unless full_width %}\n  <style>\n    .section-{{ section.id }}-settings {\n      max-width: {{ content_width }}rem;\n    }\n  </style>\n{% endunless %}\n\n{% if margin_horizontal_mobile > 0 %}\n  <style>\n    .section-{{ section.id }} {\n      border-left: solid {{ border_color }} {{ border_thickness }}px;\n      border-right: solid {{ border_color }} {{ border_thickness }}px;\n    }\n    \n    @media(min-width: 1024px) {\n      .section-{{ section.id }} {\n        border-left: 0px;\n        border-right: 0px;\n      }\n    }\n  </style>\n{% endif %}\n\n{% if margin_horizontal > 0 %}\n  <style>\n    @media(min-width: 1024px) {\n      .section-{{ section.id }} {\n        border-left: solid {{ border_color }} {{ border_thickness }}px;\n        border-right: solid {{ border_color }} {{ border_thickness }}px;\n      }\n    }\n  </style>\n{% endif %}\n\n{% if input_custom %}\n  <style>\n    .footer-newsletter-input-{{ section.id }} {\n      font-family: {{ input_font.family }}, {{ input_font.fallback_families }};\n      font-weight: {{ input_font.weight }};\n      font-style: {{ input_font.style }};\n    }\n  </style>\n{% endif %}\n\n{% if thanks_text_custom %}\n  <style>\n    .footer-newsletter-thanks-text-{{ section.id }} {\n      font-family: {{ thanks_text_font.family }}, {{ thanks_text_font.fallback_families }};\n      font-weight: {{ thanks_text_font.weight }};\n      font-style: {{ thanks_text_font.style }};\n    }\n  </style>\n{% endif %}\n\n\n{% if submit_custom %}\n  <style>\n    .footer-newsletter-submit-{{ section.id }} {\n      font-family: {{ submit_font.family }}, {{ submit_font.fallback_families }};\n      font-weight: {{ submit_font.weight }};\n      font-style: {{ submit_font.style }};\n    }\n  </style>\n{% endif %}\n\n{% if text_custom %}\n  <style>\n    .footer-text-{{ section.id }} * {\n      font-family: {{ text_font.family }}, {{ text_font.fallback_families }};\n      font-weight: {{ text_font.weight }};\n      font-style: {{ text_font.style }};\n    }\n  </style>\n{% endif %}\n\n{% if privacy_text_custom %}\n  <style>\n    .footer-privacy-text-{{ section.id }} * {\n      font-family: {{ privacy_text_font.family }}, {{ privacy_text_font.fallback_families }};\n      font-weight: {{ privacy_text_font.weight }};\n      font-style: {{ privacy_text_font.style }};\n    }\n  </style>\n{% endif %}\n\n{% if column_heading_custom %}\n  <style>\n    .footer-column-heading-{{ section.id }} {\n      font-family: {{ column_heading_font.family }}, {{ column_heading_font.fallback_families }};\n      font-weight: {{ column_heading_font.weight }};\n      font-style: {{ column_heading_font.style }};\n    }\n  </style>\n{% endif %}\n\n{% if link_custom %}\n  <style>\n    .footer-menu-link-{{ section.id }},\n    .footer-social-link-{{ section.id }} {\n      font-family: {{ link_font.family }}, {{ link_font.fallback_families }};\n      font-weight: {{ link_font.weight }};\n      font-style: {{ link_font.style }};\n    }\n  </style>\n{% endif %}\n\n{% if column_text_custom %}\n  <style>\n    .footer-column-text-{{ section.id }} {\n      font-family: {{ column_text_font.family }}, {{ column_text_font.fallback_families }};\n      font-weight: {{ column_text_font.weight }};\n      font-style: {{ column_text_font.style }};\n    }\n  </style>\n{% endif %}\n\n{% for block in section.blocks %}\n  {% case block.type %}\n    {% when 'logo' %}\n\n      <style>\n      \n      {{ block.settings.text_font | font_face: font_display: 'swap' }}\n      \n      .footer-logo-{{ block.id }} {\n        padding: {{ block_padding_vertical_mobile }}px {{ block_padding_horizontal_mobile }}px;\n        border-bottom: {{ block_border_thickness }}px solid {{ block_border_color }};\n      }\n\n      .footer-logo-image-{{ block.id }} {\n        display: block;\n        margin-left: auto;\n        margin-right: auto;\n        width: 100%;\n        max-width: {{ block.settings.image_width_mobile }}%;\n      }\n\n      .footer-logo-image-{{ block.id }} img {\n        display: block;\n        width: 100%;\n        height: 100%;\n        object-fit: cover;\n      }\n\n      .footer-logo-text-{{ block.id }} {\n        display: block;\n        text-decoration: none;\n        max-width: fit-content;\n        margin-left: auto;\n        margin-right: auto;\n      }\n\n      .footer-logo-text-{{ block.id }} * {\n        margin: 0;\n        font-size: {{ block.settings.text_size_mobile }}px;\n        color: {{ block.settings.text_color }};\n        line-height: {{ block.settings.text_height }}%;\n        text-transform: unset;\n        text-decoration: none;\n      }\n\n      @media(min-width: 1024px) {\n        \n        .footer-logo-{{ block.id }} {\n          padding: {{ block_padding_vertical }}px {{ block_padding_horizontal }}px;\n        }\n\n        .footer-logo-image-{{ block.id }} {\n          max-width: {{ block.settings.image_width }}%;\n        }\n\n        .footer-logo-text-{{ block.id }} * {\n          font-size: {{ block.settings.text_size }}px;\n        }\n      }\n    </style>\n\n    {% if block.settings.text_custom %}\n      <style>\n        .footer-logo-text-{{ block.id }} * {\n          font-family: {{ block.settings.text_font.family }}, {{ block.settings.text_font.fallback_families }};\n          font-weight: {{ block.settings.text_font.weight }};\n          font-style: {{ block.settings.text_font.style }};\n        }\n      </style>\n    {% endif %}\n\n    \n  {% endcase %}\n{% endfor %}\n\n<div class=\"section-{{ section.id }} footer-{{ section.id }}\" style=\"background-color:{{ background_color }}; background-image: {{ background_gradient }};\">\n    <div class=\"section-{{ section.id }}-settings\">\n      {% for block in section.blocks %}\n        {% if block.type == \"logo\" %}\n          <div class=\"footer-logo-{{ block.id }}\">\n            {% if block.settings.logo != blank %}\n              <a href=\"{{ shop.url }}\" class=\"footer-logo-image-{{ block.id }}\">\n                <img src=\"{{ block.settings.logo | image_url }}\" alt=\"{{ block.settings.logo.alt }}\" {% if lazy %}loading=\"lazy\"{% endif %}>\n              </a>\n            {% endif %}\n            {% if block.settings.text != blank %}\n              <a href=\"{{ shop.url }}\" class=\"footer-logo-text-{{ block.id }}\">{{ block.settings.text }}</a>\n            {% endif %}\n          </div>\n        {% endif %}\n      {% endfor %}\n\n      <div class=\"footer-body-{{ section.id }}\">\n        <div class=\"footer-left-{{ section.id }}\">\n          {% if text != blank %}\n            <div class=\"footer-text-{{ section.id }}\">\n              {{ text }}\n            </div>\n          {% endif %}\n          {% if use_newsletter %}\n            {% form 'customer', class: 'footer-newsletter-form' %}\n              <input type=\"hidden\" name=\"contact[tags]\" value=\"newsletter\">\n  \n              <div class=\"footer-newsletter-row-{{ section.id }}\">\n                <input\n                  type=\"email\"\n                  name=\"contact[email]\"\n                  class=\"footer-newsletter-input-{{ section.id }}\"\n                  value=\"{{ form.email }}\"\n                  aria-required=\"true\"\n                  autocorrect=\"off\"\n                  autocapitalize=\"off\"\n                  autocomplete=\"email\"\n                  {% if form.errors %}\n                    autofocus\n                    aria-invalid=\"true\"\n                    aria-describedby=\"Newsletter-error--{{ section.id }}\"\n                  {% elsif form.posted_successfully? %}\n                    aria-describedby=\"Newsletter-success--{{ section.id }}\"\n                  {% endif %}\n                  placeholder=\"{{ input_placeholder }}\"\n                  required\n                >\n                <button type=\"submit\" class=\"footer-newsletter-submit-{{ section.id }}\" name=\"commit\">\n                  {{ submit }}\n                </button>\n              </div>\n               {% if form.posted_successfully? %}\n                <p class=\"footer-newsletter-thanks-text-{{ section.id }}\">{{ thanks_text }}</p>\n              {% endif %}\n            {% endform %}\n          {% endif %}\n\n          {% if privacy_text != blank %}\n            <div class=\"footer-privacy-text-{{ section.id }}\">\n              {{ privacy_text }}\n            </div>\n          {% endif %}\n        </div>\n\n        <div class=\"footer-right-{{ section.id }}\">\n          {% for block in section.blocks %}\n            {% if block.type == \"column\" %}\n              <div class=\"footer-column-{{ section.id }}\">\n                {% if block.settings.heading != blank %}\n                  <p class=\"footer-column-heading-{{ section.id }}\">{{ block.settings.heading }}</p>\n                {% endif %}\n\n                {% if block.settings.menu != blank %}\n                  <ul class=\"footer-menu-list-{{ section.id }}\">\n                    {% for link in block.settings.menu.links %}\n                      <li class=\"footer-menu-item-{{ section.id }}\">\n                        <a href=\"{{ link.url }}\" class=\"footer-menu-link-{{ section.id }}\">{{ link.title }}</a>\n                      </li>\n                    {% endfor %}\n                  </ul>\n                {% endif %}\n\n              </div>\n            {% elsif block.type == \"text\" %}\n              <div class=\"footer-column-{{ section.id }} footer-text-column-{{ section.id }}\">\n                {% if block.settings.heading != blank %}\n                  <p class=\"footer-column-heading-{{ section.id }}\">{{ block.settings.heading }}</p>\n                {% endif %}\n                \n                {% if block.settings.text != blank %}\n                  <div class=\"footer-column-text-{{ section.id }}\">\n                    {{ block.settings.text }}\n                  </div>\n                {% endif %}\n                \n              </div>\n\n            {% elsif block.type == \"socials\" %}\n              <div class=\"footer-column-{{ section.id }}\">\n                {% if block.settings.heading != blank %}\n                  <p class=\"footer-column-heading-{{ section.id }}\">{{ block.settings.heading }}</p>\n                {% endif %}\n                \n                <ul class=\"footer-social-list-{{ section.id }}\">\n                  {% if block.settings.instagram != blank %}\n                    <li class=\"footer-social-item-{{ section.id }}\">\n                      <a class=\"footer-social-link-{{ section.id }}\" href=\"{{ block.settings.instagram }}\">\n                        <svg role=\"img\" viewBox=\"0 0 24 24\" xmlns=\"http://www.w3.org/2000/svg\">\n                          <title>Instagram icon</title><path d=\"M12 0C8.74 0 8.333.015 7.053.072 5.775.132 4.905.333 4.14.63c-.789.306-1.459.717-2.126 1.384S.935 3.35.63 4.14C.333 4.905.131 5.775.072 7.053.012 8.333 0 8.74 0 12s.015 3.667.072 4.947c.06 1.277.261 2.148.558 2.913.306.788.717 1.459 1.384 2.126.667.666 1.336 1.079 2.126 1.384.766.296 1.636.499 2.913.558C8.333 23.988 8.74 24 12 24s3.667-.015 4.947-.072c1.277-.06 2.148-.262 2.913-.558.788-.306 1.459-.718 2.126-1.384.666-.667 1.079-1.335 1.384-2.126.296-.765.499-1.636.558-2.913.06-1.28.072-1.687.072-4.947s-.015-3.667-.072-4.947c-.06-1.277-.262-2.149-.558-2.913-.306-.789-.718-1.459-1.384-2.126C21.319 1.347 20.651.935 19.86.63c-.765-.297-1.636-.499-2.913-.558C15.667.012 15.26 0 12 0zm0 2.16c3.203 0 3.585.016 4.85.071 1.17.055 1.805.249 2.227.415.562.217.96.477 1.382.896.419.42.679.819.896 1.381.164.422.36 1.057.413 2.227.057 1.266.07 1.646.07 4.85s-.015 3.585-.074 4.85c-.061 1.17-.256 1.805-.421 2.227-.224.562-.479.96-.899 1.382-.419.419-.824.679-1.38.896-.42.164-1.065.36-2.235.413-1.274.057-1.649.07-4.859.07-3.211 0-3.586-.015-4.859-.074-1.171-.061-1.816-.256-2.236-.421-.569-.224-.96-.479-1.379-.899-.421-.419-.69-.824-.9-1.38-.165-.42-.359-1.065-.42-2.235-.045-1.26-.061-1.649-.061-4.844 0-3.196.016-3.586.061-4.861.061-1.17.255-1.814.42-2.234.21-.57.479-.96.9-1.381.419-.419.81-.689 1.379-.898.42-.166 1.051-.361 2.221-.421 1.275-.045 1.65-.06 4.859-.06l.045.03zm0 3.678c-3.405 0-6.162 2.76-6.162 6.162 0 3.405 2.76 6.162 6.162 6.162 3.405 0 6.162-2.76 6.162-6.162 0-3.405-2.76-6.162-6.162-6.162zM12 16c-2.21 0-4-1.79-4-4s1.79-4 4-4 4 1.79 4 4-1.79 4-4 4zm7.846-10.405c0 .795-.646 1.44-1.44 1.44-.795 0-1.44-.646-1.44-1.44 0-.794.646-1.439 1.44-1.439.793-.001 1.44.645 1.44 1.439z\"></path>\n                        </svg>\n                        {{ block.settings.instagram_text }}\n                      </a>\n                    </li>\n                  {% endif %}\n                  {% if block.settings.facebook != blank %}\n                    <li class=\"footer-social-item-{{ section.id }}\">\n                      <a class=\"footer-social-link-{{ section.id }}\" href=\"{{ block.settings.facebook }}\">\n                        <svg  xmlns=\"http://www.w3.org/2000/svg\" viewBox=\"0 0 8 18\" fill=\"none\" class=\"w-16 h-16\">\n                    \t\t<path d=\"M5.15 17.14h-3.1v-8.5H0V5.72h2.06V3.99c0-2.4.62-3.85 3.35-3.85h2.27v2.94H6.26c-1.06 0-1.11.4-1.11 1.16v1.47H7.7l-.3 2.93H5.14v8.5Z\" fill=\"currentColor\"></path>\n                    \t</svg>\n                        {{ block.settings.facebook_text }}\n                      </a>\n                    </li>\n                  {% endif %}\n                  {% if block.settings.twitter != blank %}\n                    <li class=\"footer-social-item-{{ section.id }}\">\n                      <a class=\"footer-social-link-{{ section.id }}\" href=\"{{ block.settings.twitter }}\">\n                        <svg alt=\"\" width=\"19\" height=\"19\" viewBox=\"0 0 19 19\" fill=\"none\" xmlns=\"http://www.w3.org/2000/svg\">\n                          <path fill-rule=\"evenodd\" clip-rule=\"evenodd\" d=\"M19 9.5C19 14.7467 14.7467 19 9.5 19C4.25329 19 0 14.7467 0 9.5C0 4.25329 4.25329 0 9.5 0C14.7467 0 19 4.25329 19 9.5ZM8.18721 10.0675L3.64633 3.99603H7.14609L10.123 7.97639L13.8073 3.99603H14.8358L10.5825 8.59099L15.379 15.0039H11.8792L8.64689 10.6819L4.6462 15.0039H3.61771L8.18721 10.0675ZM6.76655 4.75353H5.15877L12.2586 14.2464H13.8663L6.76655 4.75353Z\" fill=\"{{ footer_border_color }}\"></path>\n                        </svg>\n                        {{ block.settings.twitter_text }}\n                      </a>\n                    </li>\n                  {% endif %}\n                  {% if block.settings.linkedin != blank %}\n                    <li class=\"footer-social-item-{{ section.id }}\">\n                      <a class=\"footer-social-link-{{ section.id }}\" href=\"{{ block.settings.linkedin }}\">\n                        <svg viewBox=\"0 0 16 16\" fill=\"none\" xmlns=\"http://www.w3.org/2000/svg\">\n                        \t<path d=\"M1.82 0C.82 0 0 .82 0 1.82v12.36C0 15.18.82 16 1.82 16h12.36c1 0 1.82-.82 1.82-1.82V1.82c0-1-.82-1.82-1.82-1.82H1.82Zm0 1.45h12.36c.2 0 .37.16.37.37v12.36c0 .2-.16.37-.37.37H1.82a.36.36 0 0 1-.37-.37V1.82c0-.2.16-.37.37-.37ZM3.95 2.7a1.25 1.25 0 1 0 0 2.5 1.25 1.25 0 0 0 0-2.5Zm6.57 3.32c-1.04 0-1.73.57-2.02 1.12h-.05v-.96H6.41v6.91h2.14V9.7c0-.9.17-1.78 1.3-1.78 1.09 0 1.1 1.02 1.1 1.82v3.36h2.14V9.3c0-1.85-.4-3.27-2.57-3.27Zm-7.61.16v6.91h2.16V6.2H2.9Z\" fill=\"currentColor\"></path>\n                    \t</svg>\n                        {{ block.settings.linkedin_text }}\n                      </a>\n                    </li>\n                  {% endif %}\n                  {% if block.settings.youtube != blank %}\n                    <li class=\"footer-social-item-{{ section.id }}\">\n                      <a class=\"footer-social-link-{{ section.id }}\" href=\"{{ block.settings.youtube }}\">\n                        <svg role=\"img\" xmlns=\"http://www.w3.org/2000/svg\" viewBox=\"0 0 24 24\">\n                          <title>YouTube icon</title><path d=\"M23.499 6.203a3.008 3.008 0 00-2.089-2.089c-1.87-.501-9.4-.501-9.4-.501s-7.509-.01-9.399.501a3.008 3.008 0 00-2.088 2.09A31.258 31.26 0 000 12.01a31.258 31.26 0 00.523 5.785 3.008 3.008 0 002.088 2.089c1.869.502 9.4.502 9.4.502s7.508 0 9.399-.502a3.008 3.008 0 002.089-2.09 31.258 31.26 0 00.5-5.784 31.258 31.26 0 00-.5-5.808zm-13.891 9.4V8.407l6.266 3.604z\"></path>\n                        </svg>\n                        {{ block.settings.youtube_text }}\n                      </a>\n                    </li>\n                  {% endif %}\n                  {% if block.settings.pinterest != blank %}\n                    <li class=\"footer-social-item-{{ section.id }}\">\n                      <a class=\"footer-social-link-{{ section.id }}\" href=\"{{ block.settings.pinterest }}\">\n                        <svg role=\"img\" viewBox=\"0 0 24 24\" xmlns=\"http://www.w3.org/2000/svg\">\n                          <title>Pinterest icon</title><path d=\"M12.017 0C5.396 0 .029 5.367.029 11.987c0 5.079 3.158 9.417 7.618 11.162-.105-.949-.199-2.403.041-3.439.219-.937 1.406-5.957 1.406-5.957s-.359-.72-.359-1.781c0-1.663.967-2.911 2.168-2.911 1.024 0 1.518.769 1.518 1.688 0 1.029-.653 2.567-.992 3.992-.285 1.193.6 2.165 1.775 2.165 2.128 0 3.768-2.245 3.768-5.487 0-2.861-2.063-4.869-5.008-4.869-3.41 0-5.409 2.562-5.409 5.199 0 1.033.394 2.143.889 2.741.099.12.112.225.085.345-.09.375-.293 1.199-.334 1.363-.053.225-.172.271-.401.165-1.495-.69-2.433-2.878-2.433-4.646 0-3.776 2.748-7.252 7.92-7.252 4.158 0 7.392 2.967 7.392 6.923 0 4.135-2.607 7.462-6.233 7.462-1.214 0-2.354-.629-2.758-1.379l-.749 2.848c-.269 1.045-1.004 2.352-1.498 3.146 1.123.345 2.306.535 3.55.535 6.607 0 11.985-5.365 11.985-11.987C23.97 5.39 18.592.026 11.985.026L12.017 0z\"></path>\n                        </svg>\n                        {{ block.settings.pinterest_text }}\n                      </a>\n                    </li>\n                  {% endif %}\n                  {% if block.settings.whatsapp != blank %}\n                    <li class=\"footer-social-item-{{ section.id }}\">\n                      <a class=\"footer-social-link-{{ section.id }}\" href=\"{{ block.settings.whatsapp }}\">\n                        <svg role=\"img\" viewBox=\"0 0 24 24\" xmlns=\"http://www.w3.org/2000/svg\">\n                          <title>WhatsApp</title><path d=\"M17.472 14.382c-.297-.149-1.758-.867-2.03-.967-.273-.099-.471-.148-.67.15-.197.297-.767.966-.94 1.164-.173.199-.347.223-.644.075-.297-.15-1.255-.463-2.39-1.475-.883-.788-1.48-1.761-1.653-2.059-.173-.297-.018-.458.13-.606.134-.133.298-.347.446-.52.149-.174.198-.298.298-.497.099-.198.05-.371-.025-.52-.075-.149-.669-1.612-.916-2.207-.242-.579-.487-.5-.669-.51-.173-.008-.371-.01-.57-.01-.198 0-.52.074-.792.372-.272.297-1.04 1.016-1.04 2.479 0 1.462 1.065 2.875 1.213 3.074.149.198 2.096 3.2 5.077 4.487.709.306 1.262.489 1.694.625.712.227 1.36.195 1.871.118.571-.085 1.758-.719 2.006-1.413.248-.694.248-1.289.173-1.413-.074-.124-.272-.198-.57-.347m-5.421 7.403h-.004a9.87 9.87 0 01-5.031-1.378l-.361-.214-3.741.982.998-3.648-.235-.374a9.86 9.86 0 01-1.51-5.26c.001-5.45 4.436-9.884 9.888-9.884 2.64 0 5.122 1.03 6.988 2.898a9.825 9.825 0 012.893 6.994c-.003 5.45-4.437 9.884-9.885 9.884m8.413-18.297A11.815 11.815 0 0012.05 0C5.495 0 .16 5.335.157 11.892c0 2.096.547 4.142 1.588 5.945L.057 24l6.305-1.654a11.882 11.882 0 005.683 1.448h.005c6.554 0 11.89-5.335 11.893-11.893a11.821 11.821 0 00-3.48-8.413Z\"></path>\n                        </svg>\n                        {{ block.settings.whatsapp_text }}\n                      </a>\n                    </li>\n                  {% endif %}\n                  {% if block.settings.tiktok != blank %}\n                    <li class=\"footer-social-item-{{ section.id }}\">\n                      <a class=\"footer-social-link-{{ section.id }}\" href=\"{{ block.settings.tiktok }}\">\n                        <svg role=\"img\" xmlns=\"http://www.w3.org/2000/svg\" viewBox=\"0 0 24 24\">\n                          <title>TikTok icon</title><path d=\"M12.525.02c1.31-.02 2.61-.01 3.91-.02.08 1.53.63 3.09 1.75 4.17 1.12 1.11 2.7 1.62 4.24 1.79v4.03c-1.44-.05-2.89-.35-4.2-.97-.57-.26-1.1-.59-1.62-.93-.01 2.92.01 5.84-.02 8.75-.08 1.4-.54 2.79-1.35 3.94-1.31 1.92-3.58 3.17-5.91 3.21-1.43.08-2.86-.31-4.08-1.03-2.02-1.19-3.44-3.37-3.65-5.71-.02-.5-.03-1-.01-1.49.18-1.9 1.12-3.72 2.58-4.96 1.66-1.44 3.98-2.13 6.15-1.72.02 1.48-.04 2.96-.04 4.44-.99-.32-2.15-.23-3.02.37-.63.41-1.11 1.04-1.36 1.75-.21.51-.15 1.07-.14 1.61.24 1.64 1.82 3.02 3.5 2.87 1.12-.01 2.19-.66 2.77-1.61.19-.33.4-.67.41-1.06.1-1.79.06-3.57.07-5.36.01-4.03-.01-8.05.02-12.07z\"></path>\n                        </svg>\n                        {{ block.settings.tiktok_text }}\n                      </a>\n                    </li>\n                  {% endif %}\n                </ul>\n              </div>\n            {% endif %}\n          {% endfor %}\n        </div>\n      </div>\n    </div>\n</div>\n\n<script>\n  function initFooter7() {\n    let thanksText = document.querySelector('.footer-newsletter-thanks-text-{{ section.id }}');\n    let submitButton = document.querySelector('.footer-newsletter-submit-{{ section.id }}');\n    \n    const url = window.location.href;\n    if (url.includes('customer_posted=true')) {\n      if(thanksText) { \n        thanksText.classList.add('active');\n        setTimeout(() => {\n          thanksText.classList.remove('active');\n        }, 5000);\n      }\n      if(submitButton) {\n        submitButton.setAttribute('disabled', true);\n      }\n    }\n\n    {% if use_redirect %}\n      const redirectUrl = '{{ redirect_url }}';\n      const delayInMilliseconds = 2000;\n    \n      if (thanksText) {\n        setTimeout(function() {\n          window.location.href = redirectUrl;\n        }, delayInMilliseconds);\n      }\n    {% endif %}\n  }\n\n  document.addEventListener('DOMContentLoaded', initFooter7);\n\n  if (Shopify.designMode) {\n     document.addEventListener('shopify:section:unload', initFooter7);\n     document.addEventListener('shopify:section:load', initFooter7);\n  }\n</script>",
  "variables": {}
}